{
    "Version": "2012-10-17",
    "Statement": [
      {
        "Effect": "Allow",
        "Principal": {
          "Service": "s3.amazonaws.com"
        },
        "Action": "SNS:Publish",
        "Resource": "arn:aws:sns:us-east-2:676206924819:image-processing-topic",
        "Condition": {
          "StringEquals": {
            "aws:SourceAccount": "676206924819"
          },
          "ArnLike": {
            "aws:SourceArn": "arn:aws:s3:::amj160-assignment3"
          }
        }
      }
    ]
  }